context_bridge/__init__.py
context_bridge/config.py
context_bridge/core.py
context_bridge/database/__init__.py
context_bridge/database/init_databases.py
context_bridge/database/postgres_manager.py
context_bridge/database/repositories/__init__.py
context_bridge/database/repositories/chunk_repository.py
context_bridge/database/repositories/document_repository.py
context_bridge/database/repositories/page_repository.py
context_bridge/database/schema/extensions.sql
context_bridge/service/__init__.py
context_bridge/service/chunking_service.py
context_bridge/service/crawling_service.py
context_bridge/service/doc_manager.py
context_bridge/service/embedding.py
context_bridge/service/search_service.py
context_bridge/service/url_service.py
context_bridge-0.1.1.dist-info/METADATA
context_bridge-0.1.1.dist-info/WHEEL
context_bridge-0.1.1.dist-info/entry_points.txt
context_bridge-0.1.1.dist-info/licenses/LICENSE
context_bridge-0.1.1.dist-info/RECORD
