Metadata-Version: 2.4
Name: context-bridge
Version: 0.1.1
Summary: Unified Python package for RAG documentation workflows - Crawl, embed, store, and retrieve technical documentation for AI agents
Project-URL: Homepage, https://github.com/Ganzzi/context_bridge
Project-URL: Documentation, https://Ganzzi.github.io/context_bridge
Project-URL: Repository, https://github.com/Ganzzi/context_bridge
Project-URL: Issues, https://github.com/Ganzzi/context_bridge/issues
Author-email: Ganzzi <boinguyen9701@gmail.com>
License: MIT
License-File: LICENSE
Keywords: ai-agents,crawling,documentation,embedding,mcp,pgvector,postgresql,rag,vector-search
Classifier: Development Status :: 3 - Alpha
Classifier: Intended Audience :: Developers
Classifier: License :: OSI Approved :: MIT License
Classifier: Programming Language :: Python :: 3
Classifier: Programming Language :: Python :: 3.11
Classifier: Programming Language :: Python :: 3.12
Classifier: Topic :: Scientific/Engineering :: Artificial Intelligence
Classifier: Topic :: Software Development :: Libraries :: Python Modules
Requires-Python: >=3.11
Requires-Dist: aiohttp>=3.9.0
Requires-Dist: crawl4ai[all]>=0.3.0
Requires-Dist: psqlpy>=0.11.0
Requires-Dist: pydantic-settings>=2.0.0
Requires-Dist: pydantic>=2.0.0
Requires-Dist: rich>=13.0.0
Requires-Dist: typer>=0.9.0
Provides-Extra: all
Requires-Dist: black>=23.0.0; extra == 'all'
Requires-Dist: mcp[cli]>=1.0.0; extra == 'all'
Requires-Dist: mkdocs-material>=9.4.0; extra == 'all'
Requires-Dist: mkdocs>=1.5.0; extra == 'all'
Requires-Dist: mkdocstrings[python]>=0.24.0; extra == 'all'
Requires-Dist: mypy>=1.5.0; extra == 'all'
Requires-Dist: pre-commit>=3.5.0; extra == 'all'
Requires-Dist: pytest-asyncio>=0.21.0; extra == 'all'
Requires-Dist: pytest-cov>=4.1.0; extra == 'all'
Requires-Dist: pytest>=7.4.0; extra == 'all'
Requires-Dist: python-dotenv>=1.0.0; extra == 'all'
Requires-Dist: ruff>=0.1.0; extra == 'all'
Requires-Dist: streamlit>=1.28.0; extra == 'all'
Provides-Extra: dev
Requires-Dist: black>=23.0.0; extra == 'dev'
Requires-Dist: mkdocs-material>=9.4.0; extra == 'dev'
Requires-Dist: mkdocs>=1.5.0; extra == 'dev'
Requires-Dist: mkdocstrings[python]>=0.24.0; extra == 'dev'
Requires-Dist: mypy>=1.5.0; extra == 'dev'
Requires-Dist: pre-commit>=3.5.0; extra == 'dev'
Requires-Dist: pytest-asyncio>=0.21.0; extra == 'dev'
Requires-Dist: pytest-cov>=4.1.0; extra == 'dev'
Requires-Dist: pytest>=7.4.0; extra == 'dev'
Requires-Dist: python-dotenv>=1.0.0; extra == 'dev'
Requires-Dist: ruff>=0.1.0; extra == 'dev'
Provides-Extra: mcp
Requires-Dist: mcp[cli]>=1.0.0; extra == 'mcp'
Provides-Extra: ui
Requires-Dist: streamlit>=1.28.0; extra == 'ui'
